my_unique_word_counter/__init__.py
my_unique_word_counter/counter.py
my_unique_word_counter-0.1.1.dist-info/LICENSE
my_unique_word_counter-0.1.1.dist-info/METADATA
my_unique_word_counter-0.1.1.dist-info/WHEEL
my_unique_word_counter-0.1.1.dist-info/top_level.txt
my_unique_word_counter-0.1.1.dist-info/RECORD
